llmbanter/banter/bot_base.py
llmbanter/banter/bot_pair.py
llmbanter/banter/bot_types.py
llmbanter/banter/conversation.py
llmbanter/bots/assistant.yaml
llmbanter/bots/evangelist/instagram.yaml
llmbanter/bots/evangelist/java_language.yaml
llmbanter/bots/evangelist/linkedin.yaml
llmbanter/bots/evangelist/python_language.yaml
llmbanter/bots/evangelist/reddit.yaml
llmbanter/bots/evangelist/tiktok.yaml
llmbanter/bots/expert/psychiatrist.yaml
llmbanter/bots/expert/python.yaml
llmbanter/bots/expert/shell.yaml
llmbanter/bots/famous/cobain.yaml
llmbanter/bots/famous/einstein.yaml
llmbanter/bots/human.yaml
llmbanter/bots/model_prompts/chatgpt.yaml
llmbanter/bots/model_prompts/claude.yaml
llmbanter/bots/social_media/reddit_negative_commenter.yaml
llmbanter/bots/social_media/reddit_positive_commenter.yaml
llmbanter/bots/system/interrogator.yaml
llmbanter/bots/system/jailbreaker.yaml
llmbanter/bots/system/questioner.yaml
llmbanter/console.py
llmbanter/library/classes.py
llmbanter/library/commands.py
llmbanter/library/consts.py
llmbanter/library/env.py
llmbanter/library/format.py
llmbanter/library/llm.py
llmbanter/library/log.py
llmbanter/library/sound.py
llmbanter-0.6.0.dist-info/LICENSE
llmbanter-0.6.0.dist-info/METADATA
llmbanter-0.6.0.dist-info/WHEEL
llmbanter-0.6.0.dist-info/entry_points.txt
llmbanter-0.6.0.dist-info/RECORD
